{"ArLeHJTeCT0Gf92oc3RThQ==":"mbr.jpg","JXkjsOtHFfD6Ohax7U/pcg==":"pu-map.png","ZgtDL74P4DoKKuN5YOT1Zw==":"mczh-tw700x700-large6550-164839763256.jpg","RbFuIdJ19aY8JWjWyTa/PQ==":"huiguan.png","bpmAmJRBP3d5vZzZ+nIEcA==":"shanmu.png","Nmec/eRdO7N9t4OPbUfm6Q==":"bosco.png","gK0kBaxkwfjxf22n66Tw9Q==":"schultz.png","OLG2c1oC32WZCTk6wtFK8Q==":"library.png","GTjy0ftLshjUMCABga/QTQ==":"gym.png","XH4Igh7dT1naasVRzyEMXQ==":"shanmu1.jpg","KHZ72fSIhTC6L6a8/HNVRw==":"messageimage-1670657676068.jpeg","Caj69u/MMQxjT6U1R9hx6Q==":"messageimage-1670657676069.jpeg","+LvI7WkoTrn7NCpxEc7q3Q==":"line-album-221206.jpg","8g/djjAhTw/M8ynaObrgHQ==":"line-album-221207.jpg","qb1479e90LZeOwcm7FWB2g==":"line-album-221208.jpg","OmXXBZyOBpK6FPQGiR6l7Q==":"line-album-221209.jpg","rijWxB1xf0LOKX/wvkn6GA==":"line-album-221211.jpg","jyb+u7HPLbXQCutmLPdxrg==":"line-album-221214.jpg","MFPFuyiaJHKqqF6mgFOZsw==":"line-album-221217.jpg","XFIiNlIAXG2iClPAvnm/Rg==":"line-album-221218.jpg","0LiQRJiyTJHtpk5bWuXIfQ==":"line-album-221227.jpg","q7pgwJWHA7AMwOjUXJwPig==":"line-album-221232.jpg","EEKM06ifTOG7FT2emIb3HQ==":"line-album-221236.jpg","R+7eHgoe9PojcczfKVhl5A==":"line-album-221238.jpg","LsU71YfbhZ6vgpWsuBj8GA==":"line-album-221239.jpg","kwoy3KOfOP9pHhqacptr3A==":"line-album-221241.jpg","scVtylmQd29Z9eTQ/nIbIA==":"line-album-221242.jpg","jaUIWzlNtloXFQ04vkQ9JA==":"brt.jpg","dkLCm9k4u8dTUrQIjY9Vlg==":"mrt.jpg","js6ssvEOYcc1H/Zz2r5oKw==":"train.jpg","8QWuknOeVDHHt6IyrqFR9Q==":".jpg","1+4X5SFqY8tqMofB8GGLyw==":"tigercity.jpg","ffywGneJDiUIVqJ0ton+aw==":"imax.jpeg","g2y2kGOuK3B7ybIhjAprMQ==":"tigercity.jpeg","JbEKQzwI3BrmWT1BksU0AQ==":"vscinema.jpeg","HmkJHdFrs5AjNMRrUY3jEw==":"2.jpeg","wDg+tsRGCEvnIx3lnlR0iA==":"-1.jpeg","PgTWVoF0Ysad2u9I+bLbig==":"-2.jpg","XEPtTTmOEFN7EERh4Z6zqw==":"silverbox1.jpg","ierD0VHQcO2pQdsb9G733g==":"silverbox.jpg","c8iVlulyiTepNPx3keXi5w==":"-2.jpeg","PYx5Yd0FVjVB7TMTRHdODw==":"holiday.jpeg","SH5gACUmX2sK/7LZqolWgA==":"holiday1.jpeg","IkrxDfvs2ovq/UwfN8Pi+g==":"silverbox.jpeg","S5+6gScto//I4anixZHwyQ==":"silverbox1.jpeg","wZoYMeaTou6/L0fmiztVdw==":"superstar.jpeg","W8c+k3HkiBQfLztuUQ5vfQ==":"holiday1-1.jpg","sOs7CZZ8w0BkNwZ59oSPnQ==":"holiday1-1.jpeg","+mW0Iu8g8DRCmpFpu7TB5w==":"superstar-1.jpg","9aNz6j6sc9+82Z8Qq1LmQA==":"superstar-1.jpeg","lOpPhAzXH7WSzpWWNOQ3iA==":"-3.jpg","0CNn/kvbKwL4ggF7C9o9Aw==":"taluan.png","/WE7JsjLzJiV4jzwU6wJnw==":"1.jpeg","Bc9RetQn4am7vmnhXkH4mA==":"jungle.jpeg","eG0tG2TyvySQ5XeRsZKgaw==":"story-1.png","IKNHSQ1RKx4Ykke0UQWq8w==":"five-seven.jpeg","gR+SyiQ1qqTncxyVRl8NeQ==":"taluan-1.png","MjGAc0l4kI5HBJXTskF6lA==":"18tc.png","5afgdbTzkXnjfGJ0oqGJQw==":"4.jpg","q8Fm0JuNCwaOr04qUaZemA==":"4.jpeg","wBhelTzOavtitt02c3sfig==":"4-1.jpeg","HAdB9I2NRRFTcJZMR3hw5Q==":"3.jpg","prlPNiQ4Yn+bS3jm+t3PeQ==":"1.png","kWAIO/CnAHh5jz9twBAvOw==":"2-1.jpeg","D+xr5iUyHHtmLFGoBDF0hw==":"3.jpeg","3EUrJnYx507B7CBD19UKoQ==":"4-2.jpeg","JbyenqnYzxODlI1E97i5UA==":"5.jpeg","ZGTg38QTfE84FkuwrGgDNg==":"8.jpg","IKzpX/hPXv4FQxc8sbh4Qg==":"9.jpg","Fa2YU3cty0w9LUKaKMWGmg==":"10.jpeg","IYFUug+/rt1At/ruCAlHgw==":"10.png","VmgzYEYLyRdhTAh1nNzPmw==":"6.jpeg","1ndlBt3yGW6bylr7VPbFPg==":"7.jpeg","rIyXk+n1XSgNPcPvKtRcng==":"8.jpeg","ZDdV9DqVFUUiEJS6ssRQmg==":"9.jpeg","kscBy0oFfzNbUSgm1q/fPA==":"16.jpg","iXKAC2E7Uyja+eXmNMa4UA==":"13.jpg","3M9l2uT1Qtfuxlo6CnC8gg==":"12.jpg","9+AWumPT6rMYKXIiEn243Q==":"13.jpeg","BAAj0Uqvj+HXJA1CAfvd5Q==":"14.jpeg","UaabTUvVNhoQh6bLxDI/qw==":"7-1.jpg","+FajU/VcrIkcuFMTJz/fcg==":"1-1.png","NgXDiLaoWyrQ0VRwHozm+A==":"1-2.png","Fq5p5OAcB+2lZFyUGgGrnw==":"7-1.jpeg","jg6+DqNyMAWWd2VhQvqUzA==":"11.jpeg","p2Kw/A5adU8H0ooe7BbCpA==":"13-1.jpeg","F5xLFgO4p5N09qpoSt/Fow==":"13-2.jpeg","8hpMq0QticR2FeFw+fM97g==":"16.jpeg","RLlwxdQOwU61Syndu1Nlhg==":"15.jpeg","GAxhrrTUqjhVSPdKBWn9bQ==":"1-1.jpg","jGTZ/v+fF13fXhfVoLPhPA==":"2-1.jpg","3GszA1aHjRKL4Zbftm9xDQ==":"3-1.jpg","XpNDM5+iACP0YcaoVa/buw==":"4-1.jpg","8FGxJCh3PEtEHwbhOcrKvA==":"5.jpg","IGYATtxr4/sEM4OkVPo7yA==":"6-1.jpg","fkT3tbybqLbtmXk4u75cmQ==":"7-2.jpg","ZOgLDHM9sLjzF5HuccPiGQ==":"8-1.jpg","XbKL1SD90vrCrxzKEIKL8w==":"9-1.jpg","8H2EhcJ0oqDNTOopPJ1bFA==":"10-1.jpg","qvZLkRSVDQfc9wGTKXbPLw==":"1-2.jpg","+O+7zcnTGJQuLcXE3ayucg==":"1-2.jpeg","zSqEMxic2cyUOtHxONFltw==":"1-1.jpeg","4hRzaQN9ZpM7Ddj5e1gqMw==":"1-3.jpg","OYnDZN3rGX81MVfbe8ySxA==":"5.5.png","bDLxdInRu050Br95OzyZSg==":"2.2.png","rDBv6k+HKlBUaL6OgvaXDA==":"3.3.jpg","+mRRBa9xx7OvGR5s823I8A==":"7.7.png","ZXxp+E4z/8GxzoV2lqWwJw==":"10.10.jpg","bBIodXn9eZ43l1LYKWPp9A==":"16.16.jpg","5jpKFTFy6e0Z1rXxqiE/Sw==":"14.14.png","k8PTKgCyd3ncAN/+MyA6NA==":"0.jpg","gjixK9LrObPE8x0Hwthlgw==":"0-1.jpg","p3fAim3NvTg+1C5bxzJLCA==":"0-2.jpg","8+MtpDdtIFxmzRBMo8C6Gg==":"0-2.jpeg","7czBWyzyqhXQVpSdIM66QA==":"0.jpeg","brroRHJMzPlBA16TNO0MlQ==":"0-1.jpeg","WuNuz/sF8U/vwYvFUVF1lg==":"hsr.jpg","xTIUpvPuouTGoeNpCFQ6Cw==":"qingshu2.jpg","a7nvwjkFuX3vnnxLM1B7Ag==":"main1.png","HI09meDabyI8roHjTxozjA==":"main1-1.png","Z18JTRa2i10zKC/KtL4nYg==":"main1-2.png","kK79kM4BPqVxs+4hTGvQCg==":"1-3.png","Wo/6fIfibyqMdc2YemTMQw==":"zhishan.jpeg","V9IlRWLCRk+yozIZl0+uLA==":"yiyuan.jpeg","yr/biWAb9c0h1yZHu9oRIQ==":"jingyuan.jpg","H5kVOUceM52gutghb6ZQDg==":"yiyuan-1.jpeg","vVSit6+NT2QDJg1iGMqXcQ==":"lupao.jpeg","P8f/WASFWIt6DovAYxu38A==":"ramon.png","Y6gGr2YV5XZ6Atqow8mY+g==":"fit.png","k9YlaPLOjEbN7DKDemuwbA==":"225371.jpeg","5U4lJAEYwuTjOWdXjK/qOQ==":"kain.jpeg","LMpesU2n22h+hLpL9ll5xg==":"0-3.jpg","xzo9elChO9JY+7V6xN91NA==":"1-4.jpg","BFxHycXc19HWnep6W6JAwg==":"1-4.jpeg","XrUO4dlcUuSj0DTCa6yOjQ==":"5-1.jpeg","0urAsoW0xvoyHMCaN1SNRQ==":"4-3.jpeg"}